ledgerclient/__init__.py
ledgerclient/api_client.py
ledgerclient/configuration.py
ledgerclient/exceptions.py
ledgerclient/rest.py
ledgerclient/schemas.py
ledgerclient/apis/__init__.py
ledgerclient/apis/path_to_api.py
ledgerclient/apis/tag_to_api.py
ledgerclient/apis/paths/__init__.py
ledgerclient/apis/paths/info.py
ledgerclient/apis/paths/ledger__info.py
ledgerclient/apis/paths/ledger_accounts.py
ledgerclient/apis/paths/ledger_accounts_address.py
ledgerclient/apis/paths/ledger_accounts_address_metadata.py
ledgerclient/apis/paths/ledger_aggregate_balances.py
ledgerclient/apis/paths/ledger_balances.py
ledgerclient/apis/paths/ledger_logs.py
ledgerclient/apis/paths/ledger_mapping.py
ledgerclient/apis/paths/ledger_script.py
ledgerclient/apis/paths/ledger_stats.py
ledgerclient/apis/paths/ledger_transactions.py
ledgerclient/apis/paths/ledger_transactions_batch.py
ledgerclient/apis/paths/ledger_transactions_txid.py
ledgerclient/apis/paths/ledger_transactions_txid_metadata.py
ledgerclient/apis/paths/ledger_transactions_txid_revert.py
ledgerclient/apis/tags/__init__.py
ledgerclient/apis/tags/accounts_api.py
ledgerclient/apis/tags/balances_api.py
ledgerclient/apis/tags/ledger_api.py
ledgerclient/apis/tags/logs_api.py
ledgerclient/apis/tags/mapping_api.py
ledgerclient/apis/tags/script_api.py
ledgerclient/apis/tags/server_api.py
ledgerclient/apis/tags/stats_api.py
ledgerclient/apis/tags/transactions_api.py
ledgerclient/model/__init__.py
ledgerclient/model/account.py
ledgerclient/model/account_response.py
ledgerclient/model/account_with_volumes_and_balances.py
ledgerclient/model/accounts_balances.py
ledgerclient/model/accounts_cursor_response.py
ledgerclient/model/aggregate_balances_response.py
ledgerclient/model/aggregated_volumes.py
ledgerclient/model/assets_balances.py
ledgerclient/model/balances_cursor_response.py
ledgerclient/model/config.py
ledgerclient/model/config_info.py
ledgerclient/model/config_info_response.py
ledgerclient/model/contract.py
ledgerclient-1.9.1.dist-info/METADATA
ledgerclient-1.9.1.dist-info/WHEEL
ledgerclient-1.9.1.dist-info/top_level.txt
ledgerclient-1.9.1.dist-info/RECORD
