Metadata-Version: 2.1
Name: ledgerclient
Version: 1.9.1
Summary: Ledger API
Home-page: UNKNOWN
Author: Numary ledger Client
Author-email: support@numary.com
License: UNKNOWN
Keywords: OpenAPI,OpenAPI-Generator,Ledger API
Platform: UNKNOWN
Requires-Python: >=3.7
Requires-Dist: certifi (>=14.5.14)
Requires-Dist: frozendict (~=2.3.4)
Requires-Dist: python-dateutil (~=2.7.0)
Requires-Dist: setuptools (>=21.0.0)
Requires-Dist: typing-extensions (~=4.3.0)
Requires-Dist: urllib3 (~=1.26.7)
